{
    "dataObj": [
        {
            "name": "Средства защиты (СИЗ). рабочая одежда и обувь",
            "total": 650000,
            "economy": 100000
        }, {
            "name": "Битум (Т) дорожный вязкий БНД 60/90 Московский НПЗ",
            "total": 550000,
            "economy": 100000
        }, {
            "name": "Труба (Т)  стальная электросварная прямошовная д х12",
            "total": 400000,
            "economy": 100000
        }, {
            "name": "Дорожный вязкий БНД 60/90 ГОСТ 22245-90 НПЗ",
            "total": 120000,
            "economy": 50000
        }
    ]
}